odoo/addons/ssi_hr_payroll_batch/README.rst
odoo/addons/ssi_hr_payroll_batch/__init__.py
odoo/addons/ssi_hr_payroll_batch/__manifest__.py
odoo/addons/ssi_hr_payroll_batch/data/approval_template_data.xml
odoo/addons/ssi_hr_payroll_batch/data/ir_sequence_data.xml
odoo/addons/ssi_hr_payroll_batch/data/policy_template_data.xml
odoo/addons/ssi_hr_payroll_batch/data/sequence_template_data.xml
odoo/addons/ssi_hr_payroll_batch/models/__init__.py
odoo/addons/ssi_hr_payroll_batch/models/hr_payslip.py
odoo/addons/ssi_hr_payroll_batch/models/hr_payslip_batch.py
odoo/addons/ssi_hr_payroll_batch/security/ir.model.access.csv
odoo/addons/ssi_hr_payroll_batch/security/ir_module_category_data.xml
odoo/addons/ssi_hr_payroll_batch/security/ir_rule_data.xml
odoo/addons/ssi_hr_payroll_batch/security/res_group_data.xml
odoo/addons/ssi_hr_payroll_batch/static/description/icon.png
odoo/addons/ssi_hr_payroll_batch/views/hr_payslip_batch_views.xml
odoo/addons/ssi_hr_payroll_batch/views/hr_payslip_views.xml
odoo14_addon_ssi_hr_payroll_batch-14.0.1.1.3.dev1.dist-info/METADATA
odoo14_addon_ssi_hr_payroll_batch-14.0.1.1.3.dev1.dist-info/WHEEL
odoo14_addon_ssi_hr_payroll_batch-14.0.1.1.3.dev1.dist-info/top_level.txt
odoo14_addon_ssi_hr_payroll_batch-14.0.1.1.3.dev1.dist-info/RECORD
